deadcode/__init__.py
deadcode/cli.py
deadcode/constants.py
deadcode/data_types.py
deadcode/actions/__init__.py
deadcode/actions/find_python_filenames.py
deadcode/actions/find_unused_names.py
deadcode/actions/fix_or_show_unused_code.py
deadcode/actions/get_unused_names_error_message.py
deadcode/actions/merge_overlaping_file_parts.py
deadcode/actions/parse_abstract_syntax_tree.py
deadcode/actions/parse_arguments.py
deadcode/actions/remove_file_parts_from_content.py
deadcode/utils/__init__.py
deadcode/utils/add_colors_to_diff.py
deadcode/utils/base_test_case.py
deadcode/utils/fix_indent.py
deadcode/utils/flatten_lists.py
deadcode/utils/nested_scopes.py
deadcode/utils/print_ast.py
deadcode/visitor/__init__.py
deadcode/visitor/code_item.py
deadcode/visitor/dead_code_visitor.py
deadcode/visitor/ignore.py
deadcode/visitor/lines.py
deadcode/visitor/noqa.py
deadcode/visitor/utils.py
deadcode-2.4.1.dist-info/METADATA
deadcode-2.4.1.dist-info/WHEEL
deadcode-2.4.1.dist-info/entry_points.txt
deadcode-2.4.1.dist-info/licenses/LICENSE
deadcode-2.4.1.dist-info/RECORD
