Metadata-Version: 2.3
Name: deadcode
Version: 2.4.1
Summary: Find and remove dead code.
Project-URL: homepage, https://github.com/albertas/deadcode
Project-URL: documentation, https://deadcode.readthedocs.io/
Author-email: Albertas Gimbutas <albertasgim@gmail.com>
License-File: LICENSE
Classifier: Development Status :: 3 - Alpha
Classifier: License :: OSI Approved :: GNU Affero General Public License v3
Classifier: Natural Language :: English
Classifier: Operating System :: OS Independent
Classifier: Programming Language :: Python
Classifier: Programming Language :: Python :: 3.10
Classifier: Programming Language :: Python :: 3.11
Classifier: Programming Language :: Python :: 3.12
Requires-Python: >=3.10
Requires-Dist: tomli>=2.0.1
Provides-Extra: test
Requires-Dist: hatch; extra == 'test'
Requires-Dist: mypy; extra == 'test'
Requires-Dist: pip-audit; extra == 'test'
Requires-Dist: pytest; extra == 'test'
Requires-Dist: pytest-cov; extra == 'test'
Requires-Dist: ruff; extra == 'test'
